.gitignore
README.rst
base.cfg
bootstrap.py
buildout.cfg
minitage-buildout.cfg
minitage-test-4.0.x.cfg
minitage-test-4.1.x.cfg
minitage-test-4.2.x.cfg
minitage.cfg
setup.cfg
setup.py
test-4.0.x.cfg
test-4.1.x.cfg
test-4.2.x.cfg
version.txt
collective.externalimageeditor-minilay/collective.externalimageeditor
collective.externalimageeditor-minilay/collective.externalimageeditor-p40
collective.externalimageeditor-minilay/collective.externalimageeditor-p41
collective.externalimageeditor-minilay/collective.externalimageeditor-p42
docs/CHANGES.rst
docs/INSTALL.rst
docs/LICENSE.GPL
docs/LICENSE.txt
scripts/sync_from_generic.sh
scripts/tests_sync_from_generic.sh
seleniums/collective.imageeditor.imacro
seleniums/collective.imageeditor.selenium
src/__init__.py
src/collective/__init__.py
src/collective.externalimageeditor.egg-info/PKG-INFO
src/collective.externalimageeditor.egg-info/SOURCES.txt
src/collective.externalimageeditor.egg-info/dependency_links.txt
src/collective.externalimageeditor.egg-info/entry_points.txt
src/collective.externalimageeditor.egg-info/namespace_packages.txt
src/collective.externalimageeditor.egg-info/requires.txt
src/collective.externalimageeditor.egg-info/top_level.txt
src/collective/externalimageeditor/__init__.py
src/collective/externalimageeditor/app_config.py
src/collective/externalimageeditor/configure.zcml
src/collective/externalimageeditor/controlpanel.py
src/collective/externalimageeditor/dashboard.py
src/collective/externalimageeditor/interfaces.py
src/collective/externalimageeditor/profiles.zcml
src/collective/externalimageeditor/rebuild_i18n.sh
src/collective/externalimageeditor/services.py
src/collective/externalimageeditor/session.py
src/collective/externalimageeditor/setuphandlers.py
src/collective/externalimageeditor/testing.py
src/collective/externalimageeditor/version.txt
src/collective/externalimageeditor/Extensions/__init__.py
src/collective/externalimageeditor/browser/__init__.py
src/collective/externalimageeditor/browser/aviary.pt
src/collective/externalimageeditor/browser/configure.zcml
src/collective/externalimageeditor/browser/externalimageeditor_viewlet.pt
src/collective/externalimageeditor/browser/methods.py
src/collective/externalimageeditor/browser/viewlet.pt
src/collective/externalimageeditor/browser/viewlets.py
src/collective/externalimageeditor/browser/resources/Edit-icon.png
