Metadata-Version: 1.0
Name: collective.externalimageeditor
Version: 1.6
Summary: Addon product for plone to edit images on online webservices
Home-page: http://www.makina-corpus.com/
Author: kiorky
Author-email: kiorky@cryptelium.net
License: GPL
Keywords: plone image editor
Platform: UNKNOWN
Classifier: Framework :: Plone
Classifier: Framework :: Plone :: 4.0
Classifier: Framework :: Plone :: 4.1
Classifier: Framework :: Plone :: 4.2
Classifier: Programming Language :: Python
Classifier: Topic :: Software Development
